kafka_utils/__init__.py
kafka_utils/confluent_producer.py
kafka_utils/consistent_partitioner.py
kafka_utils/kafka_errors.py
kafka_utils/kafka_exceptions.py
kafka_utils/kafka_msg.py
kafka_utils/kafka_python_producer.py
kafka_utils/kafka_tools.py
kafka_utils/msg_sender.py
kafka_utils/pykafka_producer.py
kafka_utils_netease-1.4.9.dist-info/LICENSE
kafka_utils_netease-1.4.9.dist-info/METADATA
kafka_utils_netease-1.4.9.dist-info/WHEEL
kafka_utils_netease-1.4.9.dist-info/top_level.txt
kafka_utils_netease-1.4.9.dist-info/RECORD
