Metadata-Version: 2.1
Name: kafka-utils-netease
Version: 1.4.9
Summary: Easy way to use Kafka in python
Home-page: UNKNOWN
Author: liuweidong
Author-email: discoheaven@163.com
License: UNKNOWN
Platform: UNKNOWN
Requires-Dist: confluent-kafka
Requires-Dist: gevent
Requires-Dist: hash-ring
